LICENSE
README.md
setup.cfg
setup.py
randoms_string_generator/__init__.py
randoms_string_generator/generator.py
randoms_string_generator.egg-info/PKG-INFO
randoms_string_generator.egg-info/SOURCES.txt
randoms_string_generator.egg-info/dependency_links.txt
randoms_string_generator.egg-info/top_level.txt